Advance/__init__.py
Advance/advancecalc.py
Basic/__init__.py
Basic/basiccalc.py
calcpack-0.1.0.dist-info/METADATA
calcpack-0.1.0.dist-info/WHEEL
calcpack-0.1.0.dist-info/top_level.txt
calcpack-0.1.0.dist-info/RECORD
