Metadata-Version: 2.4
Name: Calcpack
Version: 0.1.0
Summary: A complete package for Calculator.
Author: Bhargavi
Dynamic: author
Dynamic: summary
